pyspawner/__init__.py
pyspawner/c.py
pyspawner/client.py
pyspawner/clonefds.py
pyspawner/main.py
pyspawner/protocol.py
pyspawner/sandbox-seccomp.bpf
pyspawner/sandbox.py
pyspawner-1.0.0.dist-info/LICENSE.txt
pyspawner-1.0.0.dist-info/WHEEL
pyspawner-1.0.0.dist-info/METADATA
pyspawner-1.0.0.dist-info/RECORD
