Metadata-Version: 2.1
Name: pyspawner
Version: 1.0.0
Summary: Clone sandboxed Python processes quickly and securely, on Linux.
Home-page: https://github.com/CJWorkbench/pyspawner
License: BSD
Author: Adam Hooper
Author-email: adam@adamhooper.com
Requires-Python: >=3.7
Classifier: License :: Other/Proprietary License
Classifier: Programming Language :: Python :: 3
Classifier: Programming Language :: Python :: 3.7
Classifier: Programming Language :: Python :: 3.8
Classifier: Programming Language :: Python :: 3.9
Requires-Dist: pyroute2.minimal (>=0.6.4,<0.7.0)
Project-URL: Repository, https://github.com/CJWorkbench/pyspawner.git
